resultsbbb/__init__.py
resultsbbb-0.0.3.dist-info/METADATA
resultsbbb-0.0.3.dist-info/WHEEL
resultsbbb-0.0.3.dist-info/top_level.txt
resultsbbb-0.0.3.dist-info/RECORD
