Metadata-Version: 2.1
Name: resultsbbb
Version: 0.0.3
Summary: A basic visual package for helping Sloths team
Home-page: UNKNOWN
Author: VS
Author-email: email@gmail.com
License: UNKNOWN
Keywords: python,Sloths,360
Platform: UNKNOWN
Classifier: Development Status :: 1 - Planning
Classifier: Intended Audience :: Developers
Classifier: Programming Language :: Python :: 3
Classifier: Operating System :: Unix
Classifier: Operating System :: MacOS :: MacOS X
Classifier: Operating System :: Microsoft :: Windows
Requires-Dist: plotly
Requires-Dist: pandas
